{
  "updated": "2026-07-23T06:27:32.742155+00:00",
  "articles": [
    {
      "sourceId": "observador",
      "sourceName": "Observador",
      "color": "#e8a84c",
      "title": "Águia quer voar na Europa com capitão comprometido (até s...",
      "link": "https://observador.pt/programas/vamos-a-bola/aguia-quer-voar-na-europa-com-capitao-comprometido-ate-sair/",
      "pubDate": "Thu, 23 Jul 2026 07:22:39 +0100",
      "description": "Benfica joga hoje frente aos suiços do St. Gallen com António Silva a vestir a braçadeira de capitão. Ainda, Ibrahima Ba é o novo reforço do Sporting.",
      "thumbnail": "https://bordalo.observador.pt/v2/rs:fill:770:403/c:770:433:nowe:0:0/q:70/plain/https://s3.observador.pt/wp-content/uploads/2021/04/13151342/770-podcast-vamos-a-bola.jpg"
    },
    {
      "sourceId": "observador",
      "sourceName": "Observador",
      "color": "#e8a84c",
      "title": "As notícias das 7h",
      "link": "https://observador.pt/programas/noticiario/as-noticias-das-7h-2452/",
      "pubDate": "Thu, 23 Jul 2026 07:16:33 +0100",
      "description": "As notícias na Rádio Observador. Aconteça o que acontecer.",
      "thumbnail": "https://bordalo.observador.pt/v2/rs:fill:770:403/c:770:433:nowe:0:0/q:70/plain/https://s3.observador.pt/wp-content/uploads/2026/06/15153459/770-podcast-noticiario.png"
    },
    {
      "sourceId": "observador",
      "sourceName": "Observador",
      "color": "#e8a84c",
      "title": "Trovante, o grupo que lavrou caminho à música portuguesa",
      "link": "https://observador.pt/especiais/trovante-o-grupo-que-lavrou-caminho-para-a-musica-portuguesa/",
      "pubDate": "Thu, 23 Jul 2026 07:14:53 +0100",
      "description": "Nascido no bulício do pós-25 de abril, o Trovante teve apenas 16 anos de atividade continuada. Foi tempo suficiente para fazer a ponte entre a tradição e a modernidade e marcar gerações.",
      "thumbnail": "https://bordalo.observador.pt/v2/rs:fill:770:403/c:1399:785:nowe:0:142/q:70/plain/https://s3.observador.pt/wp-content/uploads/2026/07/22180251/trovante-1.jpg"
    },
    {
      "sourceId": "observador",
      "sourceName": "Observador",
      "color": "#e8a84c",
      "title": "Seguro recebe camisola de Vozinha",
      "link": "https://observador.pt/liveblogs/selecionador-dos-tubaroes-azuis-surpreende-seguro-com-camisola-de-vozinha/",
      "pubDate": "Thu, 23 Jul 2026 07:12:07 +0100",
      "description": "Presidente da República termina hoje visita a Cabo Verde. Ontem foi surpreendido pelo selecionador dos Tubarões Azuis com uma camisola de Vozinha.",
      "thumbnail": "https://bordalo.observador.pt/v2/rs:fill:770:403/c:1280:719:nowe:0:63/q:70/plain/https://s3.observador.pt/wp-content/uploads/2026/07/23070830/captura-de-ecra-2026-07-23-as-070817.jpg"
    },
    {
      "sourceId": "observador",
      "sourceName": "Observador",
      "color": "#e8a84c",
      "title": "Fogo no concelho de Alijó dominado",
      "link": "https://observador.pt/2026/07/23/fogo-no-concelho-de-alijo-dominado/",
      "pubDate": "Thu, 23 Jul 2026 07:08:59 +0100",
      "description": "\"O incêndio entrou em fase de resolução às 6h20\", avançou a proteção civil. Por volta das 6h40, estavam ainda 480 operacionais no local. A circulação no IC5 encontra-se normalizada desde a meia-noite.",
      "thumbnail": "https://bordalo.observador.pt/v2/rs:fill:770:403/c:2025:1138:nowe:0:106/q:70/plain/https://s3.observador.pt/wp-content/uploads/2026/07/03205836/gco-dincendio-vouzela-3-julho-2026-029.jpg"
    },
    {
      "sourceId": "rtp",
      "sourceName": "RTP Notícias",
      "color": "#e05252",
      "title": "Multiplicam-se os erros detetados na avaliação de exames",
      "link": "https://www.rtp.pt/noticias/pais/multiplicam-se-os-erros-detetados-na-avaliacao-de-exames_v1755229",
      "pubDate": "Thu, 23 Jul 2026 08:20:34 +0100",
      "description": "A RTP encontrou alunos que receberam avaliação de provas que não fizeram, outros cujos exames se perderam e ainda descontos na avaliação porque a digitalização tornou as provas ilegíveis. Ao fim da tarde de hoje ainda havia alunos sem acesso ao enunciado.",
      "thumbnail": "https://cdn-images.rtp.pt/icm/images/d3/d33a86fc81e2cf26959bf9642df6312d_N.jpg?"
    },
    {
      "sourceId": "rtp",
      "sourceName": "RTP Notícias",
      "color": "#e05252",
      "title": "Fernando Alexandre admite recuar no formato digital se problemas persistirem",
      "link": "https://www.rtp.pt/noticias/pais/fernando-alexandre-admite-recuar-no-formato-digital-se-problemas-persistirem_v1755294",
      "pubDate": "Thu, 23 Jul 2026 08:16:21 +0100",
      "description": "Ainda na Grande Entrevista da RTP, o Ministro da Educação considerou que se criou um &quot;alarmismo exagerado&quot; em torno dos exames nacionais.",
      "thumbnail": "https://cdn-images.rtp.pt/icm/images/77/77d7d76591bdf386bc62f49d834e2324_N.jpg?"
    },
    {
      "sourceId": "rtp",
      "sourceName": "RTP Notícias",
      "color": "#e05252",
      "title": "Incêndio em Alijó ameaçou aldeia de Ribalonga e cortou a IC5",
      "link": "https://www.rtp.pt/noticias/pais/incendio-em-alijo-ameacou-aldeia-de-ribalonga-e-cortou-a-ic5_v1755296",
      "pubDate": "Thu, 23 Jul 2026 08:14:47 +0100",
      "description": "Um incêndio que deflagrou pouco depois da uma da tarde, em Alijó, esteve a ameaçar a aldeia de Ribalonga.",
      "thumbnail": "https://cdn-images.rtp.pt/icm/images/da/dab4e65dbf173014911d52bbc375a1bb_N.jpg?"
    },
    {
      "sourceId": "rtp",
      "sourceName": "RTP Notícias",
      "color": "#e05252",
      "title": "Exames nacionais. Ministro assume responsabilidade por falhas",
      "link": "https://www.rtp.pt/noticias/pais/exames-nacionais-ministro-assume-responsabilidade-por-falhas_v1755295",
      "pubDate": "Thu, 23 Jul 2026 08:11:47 +0100",
      "description": "O Ministro da Educação assume-se como o &quot;último responsável&quot; pelas falhas no processo de avaliação dos exames nacionais.",
      "thumbnail": "https://cdn-images.rtp.pt/icm/images/ac/acfbf1f109e420dd484c375bfdd4155d_N.jpg?"
    },
    {
      "sourceId": "rtp",
      "sourceName": "RTP Notícias",
      "color": "#e05252",
      "title": "Dominado fogo no concelho de Alijó",
      "link": "https://www.rtp.pt/noticias/pais/dominado-fogo-no-concelho-de-alijo_n1755289",
      "pubDate": "Thu, 23 Jul 2026 08:11:09 +0100",
      "description": "O incêndio que deflagrou na quarta-feira no concelho de Alijó foi dominado hoje, às 06:20, estando os operacionais a fazer trabalhos de rescaldo em vários pontos do perímetro do fogo, disse à Lusa fonte da proteção civil.",
      "thumbnail": "https://cdn-images.rtp.pt/icm/noticias/images/8b/8b69cf9c4ff2c0e0d136cbe82b422aa7?w=350&amp;q=50&amp;rect=0,89,1500,822&amp;auto=format"
    },
    {
      "sourceId": "maisfutebol",
      "sourceName": "Maisfutebol",
      "color": "#4fc48a",
      "title": "Está cansado que o Google lhe mostre notícias de fonte duvidosa? Nós temos a solução",
      "link": "https://maisfutebol.iol.pt/google/google-search/esta-cansado-que-o-google-lhe-mostre-noticias-de-fonte-duvidosa-nos-temos-a-solucao",
      "pubDate": "Thu, 23 Jul 2026 00:42:00 +0100",
      "description": "A partir de agora já pode definir o Maisfutebol como fonte preferencial",
      "thumbnail": "https://img.iol.pt/image/id/69f8adc0d34e28842c83a37c/250"
    },
    {
      "sourceId": "maisfutebol",
      "sourceName": "Maisfutebol",
      "color": "#4fc48a",
      "title": "MAISFUTEBOL NO WHATSAPP: tudo o que é essencial está aqui",
      "link": "https://maisfutebol.iol.pt/maisfutebol/whatsapp/maisfutebol-no-whatsapp-tudo-o-que-e-essencial-esta-aqui",
      "pubDate": "Thu, 23 Jul 2026 00:42:00 +0100",
      "description": "O que de mais importante está a acontecer num único local",
      "thumbnail": "https://img.iol.pt/image/id/661b1645d34e0498921fb7f8/250"
    },
    {
      "sourceId": "maisfutebol",
      "sourceName": "Maisfutebol",
      "color": "#4fc48a",
      "title": "Estoril Open: Nuno Borges e Francisco Cabral nos «quartos» em pares",
      "link": "https://maisfutebol.iol.pt/estorilopen/estoril-open/estoril-open-tiago-torres-agarra-se-ao-sonho-e-esta-nos-quartos",
      "pubDate": "Wed, 22 Jul 2026 23:31:00 +0100",
      "description": "Terceiro dia de prova fica marcado pela eliminação de Nuno Borges nos «oitavos» e o prolongar do sonho de Tiago Torres",
      "thumbnail": "https://img.iol.pt/image/id/626d3a490cf2f9a86ea15941/250"
    },
    {
      "sourceId": "maisfutebol",
      "sourceName": "Maisfutebol",
      "color": "#4fc48a",
      "title": "Voleibol: Aboubacar Dramé Neto é reforço do Benfica",
      "link": "https://maisfutebol.iol.pt/benfica/voleibol/voleibol-aboubacar-drame-neto-e-reforco-do-benfica",
      "pubDate": "Wed, 22 Jul 2026 23:23:29 +0100",
      "description": "Internacional brasileiro assina por uma temporada",
      "thumbnail": "https://img.iol.pt/image/id/6a6142a5d34e511da0b2f2c2/250"
    },
    {
      "sourceId": "maisfutebol",
      "sourceName": "Maisfutebol",
      "color": "#4fc48a",
      "title": "Champions: Celje de Vítor Campelos empata na Albânia com «chuva» de golos",
      "link": "https://maisfutebol.iol.pt/liga-campeoes/champions/champions-celje-de-vitor-campelos-empata-na-albania-com-chuva-de-golos",
      "pubDate": "Wed, 22 Jul 2026 23:10:23 +0100",
      "description": "Empate a três golos deixa eliminatória em aberto para segunda mão, que se realiza na Eslovénia",
      "thumbnail": "https://img.iol.pt/image/id/672f9813d34e94b829073fa0/250"
    },
    {
      "sourceId": "sapo",
      "sourceName": "SAPO",
      "color": "#9b7ee8",
      "title": "Da mitigação ambiental às acessibilidades, ANA deixa cinco avisos ao Governo sobre o novo aeroporto",
      "link": "https://eco.sapo.pt/2026/07/23/da-mitigacao-ambiental-as-acessibilidades-ana-deixa-cinco-avisos-ao-governo-sobre-o-novo-aeroporto/",
      "pubDate": "Thu, 23 Jul 2026 06:20:12 +0000",
      "description": "O Relatório Técnico do aeroporto Luís de Camões deixa vários alertas. Um deles é que, com o calendário atual, só é possível ter a infraestrutura a funcionar dois anos após o que pretende o Governo.",
      "thumbnail": "https://thumbs.web.sapo.io/?H=720&W=1280&crop=center&delay_optim=1&epic=V2%3A%2FEBo8EBkZn3fL%2F33uDIcTfZnMICesud71l3NQPKiifft8yAjG3YDdLJ%2F1CDJloAW9p5BR%2FQgN6HVVxxa0XhIsdtzMHNK3BPMQaekozA8EVEM%2FFzsw2K3SyEZaomBDswF"
    },
    {
      "sourceId": "sapo",
      "sourceName": "SAPO",
      "color": "#9b7ee8",
      "title": "Seis meses de licença paga a 100%? Governo diz \"sim\" mas exige os dois meses repartidos por pai e mãe",
      "link": "https://sapo.pt/artigo/seis-meses-de-licenca-paga-a-100-governo-diz-sim-mas-exige-os-dois-meses-repartidos-por-pai-e-mae-6a61171d86e5f86c55e05c37",
      "pubDate": "Wed, 22 Jul 2026 21:41:49 +0000",
      "description": "Condição pretende aumentar número de homens que ficam com os filhos e esbater fator de desigualdade nas carreiras. Iniciativa de cidadãos quer liberdade de escolha e primeiros meses com pai e mãe em casa.",
      "thumbnail": "https://thumbs.web.sapo.io/?H=720&W=1280&crop=center&delay_optim=1&epic=V2%3AHyethFxHRTgNPEHj1eiAB%2FJlj0Ls20xQdqpviOip9PuYGWcd%2FOB2Dx0X8Z3rAgYSC7j3fd0ihoUv%2BIynCgQfcjDkAWJ3unv1VLi1dLqCLu3qJIPMhPZcOYGNpCMdt6MO"
    },
    {
      "sourceId": "sapo",
      "sourceName": "SAPO",
      "color": "#9b7ee8",
      "title": "Caso Luís Neves: PJ diz que \"não é rigoroso concluir\" que investigação lhe tenha sido retirada",
      "link": "https://sapo.pt/artigo/caso-luis-neves-pj-diz-que-nao-e-rigoroso-concluir-que-investigacao-lhe-tenha-sido-retirada-6a610d2f86e5f86c55df3768",
      "pubDate": "Wed, 22 Jul 2026 18:35:53 +0000",
      "description": "A Polícia Judiciária esclarece que o inquérito foi iniciado por “sua iniciativa”, tendo o mesmo sido remetido ao Ministério Público para \"apreciação e decisão\".",
      "thumbnail": "https://thumbs.web.sapo.io/?H=630&W=1120&crop=center&delay_optim=1&epic=V2%3A4Tu57Aho3Lt0myN7XfijKt5NCKrXkd1KDc73W2uoEaKpYh5FDwO51e7Ia%2BRk73As8Sv5H1%2B0DoLewphMjP7G%2FaeC9YtxfsaW%2BnrpF3ycif8qVQuPIEI483TuJtx3bR80"
    },
    {
      "sourceId": "sapo",
      "sourceName": "SAPO",
      "color": "#9b7ee8",
      "title": "Fernando Alexandre admite que faltou explicar a digitalização dos exames, mas fala em “alarmismo exagerado”",
      "link": "https://sapo.pt/artigo/fernando-alexandre-admite-que-faltou-explicar-a-digitalizacao-dos-exames-mas-fala-em-alarmismo-exagerado-6a6143b59c9f29b5ceec28e2",
      "pubDate": "Wed, 22 Jul 2026 22:29:02 +0000",
      "description": "O ministro da Educação rejeitou esta quarta-feira que os problemas registados na digitalização dos exames nacionais comprometam a justiça da avaliação dos alunos, falou em “alarmismo exagerado” e reiterou que a aposta na correção digital é uma...",
      "thumbnail": "https://thumbs.web.sapo.io/?H=630&W=1120&crop=center&delay_optim=1&epic=V2%3AkdKwt3%2F%2BPisFQMJ93RC7Pz76TfR0Cd%2FCM0rX0Qm6U44jf3fIv9PIuiFQTWuo1XBrl29uBzE3Szlnf4ZxPVkKm1%2BTb3vgNc%2BL7PfRpFrH8ByvVZXxrOommjfQUNkbKHQz"
    },
    {
      "sourceId": "sapo",
      "sourceName": "SAPO",
      "color": "#9b7ee8",
      "title": "Nuno Melo diz ter “muito orgulho” no ministro da Educação e destaca resultados na Administração Interna",
      "link": "https://executivedigest.sapo.pt/nuno-melo-diz-ter-muito-orgulho-no-ministro-da-educacao-e-destaca-resultados-na-administracao-interna/",
      "pubDate": "Wed, 22 Jul 2026 19:49:44 +0000",
      "description": "O presidente do CDS-PP e ministro da Defesa disse hoje ter \"muito orgulho\" em estar num Governo ao lado do ministro da Educação e, questionado sobre as polémicas que envolvem Luís Neves, destacou os resultados na área da Administração Interna.",
      "thumbnail": "https://thumbs.web.sapo.io/?H=720&W=1280&crop=center&delay_optim=1&epic=V2%3A92Nu%2BzBxQNXkcj9rG2MMjwjhlwd7HBIqgcYAEN8DmuxxMhnwnHZNKKugTSu7iinYsSz5bXXTQpvU5cDoujMRRZN3JgwzNXOJjYeI%2Fq68au2xSQEdbYo7XCY8DHW0wsuH"
    },
    {
      "sourceId": "nam",
      "sourceName": "Notícias ao Minuto",
      "color": "#e07a5f",
      "title": "Psicólogo revela as desculpas mais comuns dos \"procrastinadores crónicos\"",
      "link": "https://www.noticiasaominuto.com/lifestyle/3025517/psicologo-revela-as-desculpas-mais-comuns-dos-procrastinadores-cronicos#utm_source=rss-ultima-hora&utm_medium=rss&utm_campaign=rssfeed",
      "pubDate": "2026-07-23 07:18:06",
      "description": "",
      "thumbnail": "https://media-manager.noticiasaominuto.com/640/naom_6a60caae77626.webp?crop_params=eyJsYW5kc2NhcGUiOnsiY3JvcFdpZHRoIjoyMzk5LCJjcm9wSGVpZ2h0IjoxMzUwLCJjcm9wWCI6MTI4LCJjcm9wWSI6MzMwfX0="
    },
    {
      "sourceId": "nam",
      "sourceName": "Notícias ao Minuto",
      "color": "#e07a5f",
      "title": "José Cid \"completamente devastado\" na despedida do amigo. \"Até breve\"",
      "link": "https://www.noticiasaominuto.com/fama/3025802/jose-cid-completamente-devastado-na-despedida-do-amigo-ate-breve#utm_source=rss-ultima-hora&utm_medium=rss&utm_campaign=rssfeed",
      "pubDate": "2026-07-23 07:18:05",
      "description": "",
      "thumbnail": "https://media-manager.noticiasaominuto.com/640/naom_5416f8bc12655.webp?crop_params=eyJwb3J0cmFpdCI6eyJjcm9wV2lkdGgiOjg0MCwiY3JvcEhlaWdodCI6MTQ5MywiY3JvcFgiOjc4NiwiY3JvcFkiOjIwMH19"
    },
    {
      "sourceId": "nam",
      "sourceName": "Notícias ao Minuto",
      "color": "#e07a5f",
      "title": "Doze figuras do futebol palestiniano mortas em Gaza eram de grupo armado",
      "link": "https://www.noticiasaominuto.com/mundo/3025803/doze-figuras-do-futebol-palestiniano-mortas-em-gaza-eram-de-grupo-armado#utm_source=rss-ultima-hora&utm_medium=rss&utm_campaign=rssfeed",
      "pubDate": "2026-07-23 07:12:48",
      "description": "",
      "thumbnail": "https://media-manager.noticiasaominuto.com/640/naom_656092b7cc778.webp"
    },
    {
      "sourceId": "nam",
      "sourceName": "Notícias ao Minuto",
      "color": "#e07a5f",
      "title": "Após explosões, Japão realiza com sucesso teste de novo foguetão",
      "link": "https://www.noticiasaominuto.com/tech/3025793/apos-explosoes-japao-realiza-com-sucesso-teste-de-novo-foguetao#utm_source=rss-ultima-hora&utm_medium=rss&utm_campaign=rssfeed",
      "pubDate": "2026-07-23 07:11:47",
      "description": "",
      "thumbnail": "https://media-manager.noticiasaominuto.com/640/naom_6a61b047a6e64.webp?crop_params=eyJsYW5kc2NhcGUiOnsiY3JvcFdpZHRoIjo2MzEsImNyb3BIZWlnaHQiOjM1NSwiY3JvcFgiOjIsImNyb3BZIjoyNDh9LCJwb3J0cmFpdCI6eyJjcm9wV2lkdGgiOjM3OSwiY3JvcEhlaWdodCI6Njc1LCJjcm9wWCI6MTE4LCJjcm9wWSI6Nn19"
    },
    {
      "sourceId": "nam",
      "sourceName": "Notícias ao Minuto",
      "color": "#e07a5f",
      "title": "Câmara dos Representantes aprova 83,3 mil miljhões para guerra com Irão",
      "link": "https://www.noticiasaominuto.com/mundo/3025801/camara-dos-representantes-aprova-83-3-mil-miljhoes-para-guerra-com-irao#utm_source=rss-ultima-hora&utm_medium=rss&utm_campaign=rssfeed",
      "pubDate": "2026-07-23 07:10:30",
      "description": "",
      "thumbnail": "https://media-manager.noticiasaominuto.com/640/naom_651dc1e7c917e.webp"
    },
    {
      "sourceId": "pplware",
      "sourceName": "Pplware",
      "color": "#5bc4d4",
      "title": "Só precisa do iPad para usar o WhatsApp e há novidades no Android Auto",
      "link": "https://pplware.sapo.pt/apple/ja-so-precisa-do-ipad-para-usar-o-whatsapp-e-novidades-no-android-auto/",
      "pubDate": "Thu, 23 Jul 2026 06:00:17 +0000",
      "description": "A forma como os utilizadores comunicam está em constante mudança, deixando de estar confinada apenas ao ecrã do smartphone. O WhatsApp mostra isso com a novidade revelada. Já se pode usar apenas o iPad&#46;&#46;&#46;",
      "thumbnail": "https://pplware.sapo.pt/wp-content/uploads/2026/07/whatsapp_ipad.jpg"
    },
    {
      "sourceId": "pplware",
      "sourceName": "Pplware",
      "color": "#5bc4d4",
      "title": "Apple Watch volta a salvar uma vida: queda em trilho ativou automaticamente o socorro",
      "link": "https://pplware.sapo.pt/apple/apple-watch-volta-a-salvar-uma-vida-queda-em-trilho-ativou-automaticamente-o-socorro/",
      "pubDate": "Wed, 22 Jul 2026 21:30:59 +0000",
      "description": "A Apple voltou a destacar um caso real em que o Apple Watch foi determinante para salvar uma vida. A empresa partilhou um novo vídeo onde mostra como as funcionalidades Deteção de Queda e&#46;&#46;&#46;",
      "thumbnail": "https://pplware.sapo.pt/wp-content/uploads/2026/07/apple_watch_salvou00.webp"
    },
    {
      "sourceId": "pplware",
      "sourceName": "Pplware",
      "color": "#5bc4d4",
      "title": "Light Flip: depois de anos esquecido, o telemóvel com tampa está de volta",
      "link": "https://pplware.sapo.pt/gadgets/light-flip-depois-de-anos-esquecido-o-telemovel-com-tampa-esta-de-volta/",
      "pubDate": "Wed, 22 Jul 2026 20:30:53 +0000",
      "description": "A Light, empresa norte-americana conhecida pelos seus modelos de telemóvel minimalistas, apresentou o Light Flip, um dispositivo que recupera o formato clássico dos anos 2000 para oferecer uma experiência sem redes sociais, sem publicidade&#46;&#46;&#46;",
      "thumbnail": "https://pplware.sapo.pt/wp-content/uploads/2026/07/light-flip04.jpg"
    },
    {
      "sourceId": "pplware",
      "sourceName": "Pplware",
      "color": "#5bc4d4",
      "title": "Quando o cruise control parecia impossível de desligar: três casos que fizeram história",
      "link": "https://pplware.sapo.pt/motores/quando-o-cruise-control-parecia-impossivel-de-desligar-tres-casos-que-fizeram-historia/",
      "pubDate": "Wed, 22 Jul 2026 19:30:42 +0000",
      "description": "Com tanta tecnologia, será que os carros podem “tomar conta” e desobedecer à vontade do condutor? Na história há exemplos. Lembra-se do cruise control preso? Os automóveis atuais estão repletos de tecnologia e sistemas&#46;&#46;&#46;",
      "thumbnail": "https://pplware.sapo.pt/wp-content/uploads/2026/07/imagem_cruise_control00.webp"
    },
    {
      "sourceId": "pplware",
      "sourceName": "Pplware",
      "color": "#5bc4d4",
      "title": "Substack declara guerra aos textos falsos e lança detetor de inteligência artificial",
      "link": "https://pplware.sapo.pt/inteligencia-artificial/substack-declara-guerra-aos-textos-falsos-e-lanca-detetor-de-inteligencia-artificial/",
      "pubDate": "Wed, 22 Jul 2026 19:00:24 +0000",
      "description": "A plataforma de newsletters Substack anunciou uma nova funcionalidade que procura identificar se os conteúdos publicados foram gerados por sistemas de inteligência artificial (IA). Esta medida pretende combater a proliferação de textos automatizados e&#46;&#46;&#46;",
      "thumbnail": "https://pplware.sapo.pt/wp-content/uploads/2026/07/substack.webp"
    },
    {
      "sourceId": "autosport",
      "sourceName": "Autosport",
      "color": "#f0c040",
      "title": "Baja Aragon: a comunicação do governo local na íntegra",
      "link": "https://www.autosport.pt/todooterreno/baja-aragon-a-comunicacao-do-governo-local-na-integra/",
      "pubDate": "Wed, 22 Jul 2026 18:20:09 +0000",
      "description": "A Baja España-Aragón 2026, prova que deveria decorrer entre 24 e 26 de julho, foi oficialmente suspensa pelo Governo de Aragão devido ao risco extremo de incêndios florestais e às condições meteorológicas adversas na região de Teruel, estando a organização a trabalhar com as autoridades para encontr",
      "thumbnail": ""
    },
    {
      "sourceId": "autosport",
      "sourceName": "Autosport",
      "color": "#f0c040",
      "title": "Vendas na Europa crescem 13% em junho",
      "link": "https://www.autosport.pt/sem-categoria/vendas-na-europa-crescem-13-em-junho/",
      "pubDate": "Wed, 22 Jul 2026 17:34:00 +0000",
      "description": "Por José Caetano As matrículas de automóveis novos na Europa registaram um crescimento de 13% em junho, comparativamente ao mesmo mês do ano passado, atingindo o total de 1,38 milhões de unidades, impulsionadas, sobretudo, pela forte procura de carros equipados com motorizações elétricas, que dispar",
      "thumbnail": ""
    },
    {
      "sourceId": "autosport",
      "sourceName": "Autosport",
      "color": "#f0c040",
      "title": "Baja Aragon suspensa devido ao risco de “extremo” de incêndios",
      "link": "https://www.autosport.pt/todooterreno/baja-aragon-suspensa-devido-ao-risco-de-extremo-de-incendios/",
      "pubDate": "Wed, 22 Jul 2026 17:30:00 +0000",
      "description": "Governo de Aragão adia prova e procura nova data A Baja España-Aragón 2026, prevista para 24 a 26 de julho, foi suspensa pelo Governo de Aragão devido ao risco extremo de incêndios florestais. A organização e as autoridades regionais vão agora trabalhar para encontrar uma nova data ainda durante est",
      "thumbnail": ""
    },
    {
      "sourceId": "autosport",
      "sourceName": "Autosport",
      "color": "#f0c040",
      "title": "Cupra Raval: versão Plus por 29.000 €",
      "link": "https://www.autosport.pt/automais/cupra-raval-versao-plus-por-29-000-e/",
      "pubDate": "Wed, 22 Jul 2026 16:27:00 +0000",
      "description": "Por João Isaac A Cupra anunciou a introdução do Raval Plus, versão que não é mais do que uma fórmula mais acessível de acesso à gama do novo segmento B elétrico. Nesta proposta, motor elétrico de 99 kW (135 cv) alimentado por uma bateria LFP com 38,5 kWh de capacidade bruta (37 kWh úteis), combinaçã",
      "thumbnail": ""
    },
    {
      "sourceId": "autosport",
      "sourceName": "Autosport",
      "color": "#f0c040",
      "title": "Petroprix reforça presença ibérica",
      "link": "https://www.autosport.pt/automais/petroprix-reforca-presenca-iberica/",
      "pubDate": "Wed, 22 Jul 2026 16:20:00 +0000",
      "description": "Por Pedro Junceiro A Petroprix anunciou a aquisição da totalidade da rede de 40 postos de abastecimento do Grupo Eroski, naquela que representa a maior operação da sua história. O negócio, cuja conclusão está prevista até ao final do ano, permitirá à operadora de combustíveis “low-cost” reforçar sig",
      "thumbnail": ""
    }
  ]
}