{
  "updated": "2026-07-14T20:07:36.170529+00:00",
  "articles": [
    {
      "sourceId": "observador",
      "sourceName": "Observador",
      "color": "#e8a84c",
      "title": "“Saber de monstros imaginários prepara-nos para os reais”",
      "link": "https://observador.pt/programas/convidado-extra/samuel-f-pimenta-saber-de-monstros-imaginarios-prepara-nos-para-os-reais/",
      "pubDate": "Tue, 14 Jul 2026 20:56:36 +0100",
      "description": "No “Atlas das Criaturas Mágicas de Portugal”, do poeta e escritor Samuel Pimenta, ficamos a saber que quando os mouros nos invadiram no séc. VIII as mouras encantadas já povoavam o nosso imaginário.",
      "thumbnail": "https://bordalo.observador.pt/v2/rs:fill:770:403/c:770:433:nowe:0:0/q:70/plain/https://s3.observador.pt/wp-content/uploads/2021/04/13105535/770-podcast-convidado-extra.jpg"
    },
    {
      "sourceId": "observador",
      "sourceName": "Observador",
      "color": "#e8a84c",
      "title": "Homem de 74 anos será pessoa mais velha executada na Flórida",
      "link": "https://observador.pt/2026/07/14/homem-de-74-anos-sera-a-pessoa-mais-velha-a-ser-executada-na-florida/",
      "pubDate": "Tue, 14 Jul 2026 20:43:04 +0100",
      "description": "Homem foi condenado em 1987 pela morte de uma jovem. Até ao final do mês, um outro condenado, de 80 anos, também deverá ser executado.",
      "thumbnail": "https://bordalo.observador.pt/v2/rs:fill:770:403/c:3457:1944:nowe:0:244/q:70/plain/https://s3.observador.pt/wp-content/uploads/2026/07/14190527/gettyimages-855665604.jpg"
    },
    {
      "sourceId": "observador",
      "sourceName": "Observador",
      "color": "#e8a84c",
      "title": "Ann Widdecombe deu entrevista 20 minutos antes de ser morta",
      "link": "https://observador.pt/2026/07/14/ha-muito-que-existe-um-jogo-de-destruicao-contra-politicos-ann-widdecombe-deu-entrevista-20-minutos-antes-de-ser-morta/",
      "pubDate": "Tue, 14 Jul 2026 20:41:58 +0100",
      "description": "Três dias após Farage renunciar ao mandato de deputado, antiga porta-voz do Reform UK deu uma entrevista a defendê-lo. Vinte minutos depois foi morta. Família aceitou agora divulgação de excerto.",
      "thumbnail": "https://bordalo.observador.pt/v2/rs:fill:770:403/c:4096:2298:nowe:0:144/q:70/plain/https://s3.observador.pt/wp-content/uploads/2026/07/10201343/gettyimages-2158872982-scaled.jpg"
    },
    {
      "sourceId": "observador",
      "sourceName": "Observador",
      "color": "#e8a84c",
      "title": "Terapêutica para Alzheimer vence Prémio Bluepharma",
      "link": "https://observador.pt/2026/07/14/universidade-de-coimbra-terapeutica-para-doencas-neurodegenerativas-vence-premio-bluepharma/",
      "pubDate": "Tue, 14 Jul 2026 20:39:36 +0100",
      "description": "Investigadores da UC identificaram um mecanismo biológico inédito ligado à propagação da proteína tau e desenvolvem estratégia para a bloquear. Prémio vale até 50 mil euros.",
      "thumbnail": "https://bordalo.observador.pt/v2/rs:fill:770:403/c:770:433:nowe:0:0/q:70/plain/https://s3.observador.pt/wp-content/uploads/2020/11/05065326/cuidadores-dsc01372-1_770x433_acf_cropped-1.jpg"
    },
    {
      "sourceId": "observador",
      "sourceName": "Observador",
      "color": "#e8a84c",
      "title": "Trump. \"Está a mandar o barro à parede a ver se fica\"",
      "link": "https://observador.pt/programas/gabinete-de-guerra/trump-esta-a-mandar-o-barro-a-parede-a-ver-se-fica/",
      "pubDate": "Tue, 14 Jul 2026 20:35:01 +0100",
      "description": "António José Telo afirma que Donald Trump usa propostas radicais para testar reações. O antigo professor na Academia Militar crê que o presidente americano negoceia para tornar a guerra rentável.",
      "thumbnail": "https://bordalo.observador.pt/v2/rs:fill:770:403/c:770:433:nowe:0:0/q:70/plain/https://s3.observador.pt/wp-content/uploads/2024/04/15124755/770-podcast-gabinete-de-guerra.jpg"
    },
    {
      "sourceId": "rtp",
      "sourceName": "RTP Notícias",
      "color": "#e05252",
      "title": "Tropas de mais de 30 países desfilaram em Paris no Dia da Bastilha",
      "link": "https://www.rtp.pt/noticias/mundo/tropas-de-mais-de-30-paises-desfilaram-em-paris-no-dia-da-bastilha_v1753374",
      "pubDate": "Tue, 14 Jul 2026 22:03:47 +0100",
      "description": "O desfile militar do Dia Nacional de França foi histórico. Nunca houve tantas tropas juntas, mais de 7.000 e nunca antes tinham estado tantos soldados estrangeiros convidados.",
      "thumbnail": "https://cdn-images.rtp.pt/icm/images/eb/eb1588386b59f7c0d5e125964ae6c611_N.jpg?"
    },
    {
      "sourceId": "rtp",
      "sourceName": "RTP Notícias",
      "color": "#e05252",
      "title": "Calor. Morreram 396 pessoas em Portugal no dia 6 de julho",
      "link": "https://www.rtp.pt/noticias/pais/calor-morreram-396-pessoas-em-portugal-no-dia-6-de-julho_v1753371",
      "pubDate": "Tue, 14 Jul 2026 21:57:47 +0100",
      "description": "Morreram 396 pessoas em Portugal apenas no dia 6 de julho deste ano. A maior parte eram pessoas com 65 anos ou mais.",
      "thumbnail": "https://cdn-images.rtp.pt/icm/images/7f/7fea527e55e48d9e55ad64f508dd156e_N.jpg?"
    },
    {
      "sourceId": "rtp",
      "sourceName": "RTP Notícias",
      "color": "#e05252",
      "title": "Almada. Consumidores podem pedir indemnização por falta de água",
      "link": "https://www.rtp.pt/noticias/pais/almada-consumidores-podem-pedir-indemnizacao-por-falta-de-agua_v1753370",
      "pubDate": "Tue, 14 Jul 2026 21:55:47 +0100",
      "description": "A ministra do Ambiente diz que os moradores de Almada que ficaram sem água podem pedir uma compensação financeira.",
      "thumbnail": "https://cdn-images.rtp.pt/icm/images/aa/aa45e72dfdd19834a300efdfedd0c361_N.jpg?"
    },
    {
      "sourceId": "rtp",
      "sourceName": "RTP Notícias",
      "color": "#e05252",
      "title": "André Ventura alvo de inquérito por \"comportamento inaceitável\"",
      "link": "https://www.rtp.pt/noticias/pais/andre-ventura-alvo-de-inquerito-por-comportamento-inaceitavel_v1753369",
      "pubDate": "Tue, 14 Jul 2026 21:53:47 +0100",
      "description": "O presidente da Assembleia da República pediu a abertura de um inquérito sobre a conduta de André Ventura.",
      "thumbnail": "https://cdn-images.rtp.pt/icm/images/04/0436e25ad5d9d50a85b7db3a16c042ba_N.jpg?"
    },
    {
      "sourceId": "rtp",
      "sourceName": "RTP Notícias",
      "color": "#e05252",
      "title": "Câmara de Odemira está a averiguar legalidade das obras em imóvel do MAI",
      "link": "https://www.rtp.pt/noticias/pais/camara-de-odemira-esta-a-averiguar-legalidade-das-obras-em-imovel-do-mai_n1753365",
      "pubDate": "Tue, 14 Jul 2026 21:49:16 +0100",
      "description": "A Câmara de Odemira está a investigar as obras na casa do ministro da Administração Interna por suspeita de irregularidades.",
      "thumbnail": "https://cdn-images.rtp.pt/icm/noticias/images/3d/3df2197323ea6f3705a340c980a4a8c4?w=350&amp;q=50&amp;rect=0,195,4898,2685&amp;auto=format"
    },
    {
      "sourceId": "maisfutebol",
      "sourceName": "Maisfutebol",
      "color": "#4fc48a",
      "title": "Mourinho assiste ao França-Espanha com a restante equipa técnica",
      "link": "https://maisfutebol.iol.pt/mundial-2026/mundial2026/mourinho-assiste-ao-franca-espanha-com-a-restante-equipa-tecnica",
      "pubDate": "Tue, 14 Jul 2026 20:36:27 +0100",
      "description": "Técnico partilha imagem nas redes sociais enquanto se encontra no centro de treinos do Real Madrid",
      "thumbnail": "https://img.iol.pt/image/id/6a568e0fd34ef04b4f3f68c6/250"
    },
    {
      "sourceId": "maisfutebol",
      "sourceName": "Maisfutebol",
      "color": "#4fc48a",
      "title": "Euromilhões: a chave do sorteio desta terça-feira",
      "link": "https://maisfutebol.iol.pt/euromilhoes/jackpot-euromilhoes/euromilhoes-a-chave-do-sorteio-desta-terca-feira-178405754",
      "pubDate": "Tue, 14 Jul 2026 20:32:25 +0100",
      "description": "Jackpot de 38 milhões de euros",
      "thumbnail": "https://img.iol.pt/image/id/61bceacb0cf2cc58e7d83686/250"
    },
    {
      "sourceId": "maisfutebol",
      "sourceName": "Maisfutebol",
      "color": "#4fc48a",
      "title": "Jesse Derry: «Rui Borges é fantástico»",
      "link": "https://maisfutebol.iol.pt/sporting/celtic/jesse-derry-rui-borges-e-fantastico",
      "pubDate": "Tue, 14 Jul 2026 20:24:52 +0100",
      "description": "Sporting-Celtic, 3-1 (reportagem)",
      "thumbnail": "https://img.iol.pt/image/id/6a56753ed34e511da0b2d50d/250"
    },
    {
      "sourceId": "maisfutebol",
      "sourceName": "Maisfutebol",
      "color": "#4fc48a",
      "title": "Jesse Derry: «O estilo de jogo do Sporting ajuda-me»",
      "link": "https://maisfutebol.iol.pt/sporting/celtic/jesse-derry-o-estilo-de-jogo-do-sporting-ajuda-me",
      "pubDate": "Tue, 14 Jul 2026 20:22:18 +0100",
      "description": "Sporting-Celtic, 4-1 (reportagem)",
      "thumbnail": "https://img.iol.pt/image/id/6a539d0dd34e511da0b2cc60/250"
    },
    {
      "sourceId": "maisfutebol",
      "sourceName": "Maisfutebol",
      "color": "#4fc48a",
      "title": "Jesse Derry: «Jogar com o número do Ronaldo é um privilégio»",
      "link": "https://maisfutebol.iol.pt/jesse-derry/sporting/jesse-derry-jogar-com-o-numero-do-ronaldo-e-um-privilegio",
      "pubDate": "Tue, 14 Jul 2026 20:17:35 +0100",
      "description": "Sporting-Celtic, 4-1 (reportagem)",
      "thumbnail": "https://img.iol.pt/image/id/6a539d0dd34ef04b4f3f6004/250"
    },
    {
      "sourceId": "sapo",
      "sourceName": "SAPO",
      "color": "#9b7ee8",
      "title": "União Europeia vive “Super Terça-feira” histórica do alargamento",
      "link": "https://sapo.pt/artigo/uniao-europeia-vive-super-terca-feira-historica-do-alargamento-6a5674c54435ce834e1d5f48",
      "pubDate": "Tue, 14 Jul 2026 17:45:34 +0000",
      "description": "Montenegro, Albânia, Moldávia e Ucrânia, os países que lideram o processo de adesão, deram passos importantes nas negociações. Algo que, segundo Marta Kos, não acontecia há mais de 20 anos.",
      "thumbnail": "https://thumbs.web.sapo.io/?H=675&W=1200&crop=center&delay_optim=1&epic=V2%3AebYVO9mzZOFUdLgS6aS4eNHanMP6Ffm7LPJ22HkWAK64CNtW5UDro0DPTgDqbxb9N4AaLJEgzbRMp2mO26WHJRn2XzpdMYGhjE3Twvp9Vc7d3ZKOd5sGINcOrUZfFNLb"
    },
    {
      "sourceId": "sapo",
      "sourceName": "SAPO",
      "color": "#9b7ee8",
      "title": "Reforma laboral. Ministra vai \"devolver palavra\" a parceiros",
      "link": "https://sapo.pt/artigo/reforma-laboral-ministra-vai-devolver-palavra-a-parceiros-6a566da851114f8fcdf12596",
      "pubDate": "Tue, 14 Jul 2026 17:45:34 +0000",
      "description": "Levantando a ponta do véu para a reunião da concertação social desta quarta-feira, Palma Ramalho diz querer ouvir parceiros sobre novo caminho da reforma laboral. Salário mínimo para 2027 em aberto.",
      "thumbnail": "https://thumbs.web.sapo.io/?H=720&W=1280&crop=center&delay_optim=1&epic=V2%3AmvA1s6pe9CNeGYQSuXZcl3Qi2Y2Q4LZuvtDdEf%2BHuXlcTBCEWC8s8KslKlrRMtbykwgqHMOiP1Ov0n7o59DcK1Y6GD5bNj0YNRbf9oV9uVQFpW8tcoXDVKXQ19EJCh86"
    },
    {
      "sourceId": "sapo",
      "sourceName": "SAPO",
      "color": "#9b7ee8",
      "title": "Abusos sexuais. Igreja quer colaborar com sociedade civil",
      "link": "https://sapo.pt/artigo/abusos-sexuais-igreja-quer-colaborar-com-sociedade-civil-6a5674c451114f8fcdf23433",
      "pubDate": "Tue, 14 Jul 2026 17:45:34 +0000",
      "description": "O porta-voz da Conferência Episcopal Portuguesa contestou o silêncio do Estado nos apoios às vítimas de abusos sexuais na Igreja Católica. As vítimas vão receber entre 9 mil e 45 mil euros.",
      "thumbnail": "https://thumbs.web.sapo.io/?H=465&W=826&crop=center&delay_optim=1&epic=V2%3A4d2p3RBuP5XzUSC4nwSi7h3W0ugHOZzI83CL5RLeZxQ5he5%2BWeQLvjp7fkGySNM0haANDqHi7Am5NOMwDAGkkLX6ckmX%2FBlot3wJrbtWcu7uZaeSyGYQQemr%2FGQwqIF%2F"
    },
    {
      "sourceId": "sapo",
      "sourceName": "SAPO",
      "color": "#9b7ee8",
      "title": "Encontrado morto jovem de 17 anos que desapareceu no Rio Douro no Porto",
      "link": "https://sapo.pt/artigo/encontrado-morto-jovem-de-17-anos-que-desapareceu-no-rio-douro-no-porto-6a5674c980bc0ba849a9f36f",
      "pubDate": "Tue, 14 Jul 2026 17:45:34 +0000",
      "description": "O adolescente estaria a dar mergulhos com um grupo de amigos entre Cais do Ouro e ao Cais da Secil. O alerta foi dado pelas 15:15 desta terça-feira.",
      "thumbnail": "https://thumbs.web.sapo.io/?H=550&W=977&crop=center&delay_optim=1&epic=V2%3ADJpDZY6Svab98EkQ7ruKu33jX6ChS9W4pP7%2F6k3mu0npl8%2BFt0Mkt6pgzfpAnYKLaDL1vp5dzCAoAvWtTfxgMCPhswj7xuyn7mELfQZDDPD1p1jEmJ90Nl9UNX45H6oB"
    },
    {
      "sourceId": "sapo",
      "sourceName": "SAPO",
      "color": "#9b7ee8",
      "title": "Ministra do Ambiente responsabiliza Câmara de Almada e SMAS pela crise da água",
      "link": "https://eco.sapo.pt/2026/07/14/ministra-do-ambiente-responsabiliza-camara-de-almada-e-smas-pela-crise-da-agua/",
      "pubDate": "Tue, 14 Jul 2026 17:45:34 +0000",
      "description": "Ministra aponta perdas de água superiores à média nacional e investimento insuficiente na renovação da rede em Almada. E garante compensação para consumidores afetados por interrupções prolongadas.",
      "thumbnail": "https://thumbs.web.sapo.io/?H=720&W=1280&crop=center&delay_optim=1&epic=V2%3AsSoJWrFSfz2%2B8irOnvicgRTnwKdBEJ2%2Foclpu%2Byp2KgZd6xA3lTICB2s%2FgxuAor7bhpmoZZFx2Rr5e24IBdjgPzZ%2BlRpKwANkusrUhbhLQ9MsVPOnUx%2B144feVQoHNpD"
    },
    {
      "sourceId": "nam",
      "sourceName": "Notícias ao Minuto",
      "color": "#e07a5f",
      "title": "Mais investimento não trava estagnação da reciclagem em Portugal",
      "link": "https://www.noticiasaominuto.com/pais/3021516/mais-investimento-nao-trava-estagnacao-da-reciclagem-em-portugal#utm_source=rss-ultima-hora&utm_medium=rss&utm_campaign=rssfeed",
      "pubDate": "2026-07-14 21:05:40",
      "description": "",
      "thumbnail": "https://media-manager.noticiasaominuto.com/640/naom_68808c474a11e.webp?crop_params=eyJsYW5kc2NhcGUiOnsiY3JvcFdpZHRoIjoyNDk4LCJjcm9wSGVpZ2h0IjoxNDA1LCJjcm9wWCI6OCwiY3JvcFkiOjM1fX0="
    },
    {
      "sourceId": "nam",
      "sourceName": "Notícias ao Minuto",
      "color": "#e07a5f",
      "title": "Cuidado! Eis o que acontece realmente quando faz xixi na piscina",
      "link": "https://www.noticiasaominuto.com/lifestyle/3021476/cuidado-eis-o-que-acontece-realmente-quando-faz-xixi-na-piscina#utm_source=rss-ultima-hora&utm_medium=rss&utm_campaign=rssfeed",
      "pubDate": "2026-07-14 21:02:39",
      "description": "",
      "thumbnail": "https://media-manager.noticiasaominuto.com/640/naom_6a567aed6c656.webp"
    },
    {
      "sourceId": "nam",
      "sourceName": "Notícias ao Minuto",
      "color": "#e07a5f",
      "title": "Casos de mutilação genital feminina sobem para 292 em Portugal",
      "link": "https://www.noticiasaominuto.com/pais/3021524/casos-de-mutilacao-genital-feminina-sobem-para-292-em-portugal#utm_source=rss-ultima-hora&utm_medium=rss&utm_campaign=rssfeed",
      "pubDate": "2026-07-14 21:02:31",
      "description": "",
      "thumbnail": "https://media-manager.noticiasaominuto.com/640/naom_6a5695453fce9.webp?crop_params=eyJsYW5kc2NhcGUiOnsiY3JvcFdpZHRoIjoyNDAwLCJjcm9wSGVpZ2h0IjoxMzUwLCJjcm9wWCI6MCwiY3JvcFkiOjB9LCJwb3J0cmFpdCI6eyJjcm9wV2lkdGgiOjc1NCwiY3JvcEhlaWdodCI6MTM0MCwiY3JvcFgiOjg0OCwiY3JvcFkiOjEwfX0="
    },
    {
      "sourceId": "nam",
      "sourceName": "Notícias ao Minuto",
      "color": "#e07a5f",
      "title": "Lee Hyunju reforça opções de Vasco Seabra no estágio do Arouca",
      "link": "https://www.noticiasaominuto.com/desporto/3021497/lee-hyunju-reforca-opcoes-de-vasco-seabra-no-estagio-do-arouca#utm_source=rss-ultima-hora&utm_medium=rss&utm_campaign=rssfeed",
      "pubDate": "2026-07-14 20:49:28",
      "description": "",
      "thumbnail": "https://media-manager.noticiasaominuto.com/640/naom_65457063c20ad.webp?crop_params=eyJsYW5kc2NhcGUiOnsiY3JvcFdpZHRoIjoyNTYwLCJjcm9wSGVpZ2h0IjoxNDQwLCJjcm9wWCI6MCwiY3JvcFkiOjQ3fSwicG9ydHJhaXQiOnsiY3JvcFdpZHRoIjo5NDksImNyb3BIZWlnaHQiOjE2ODcsImNyb3BYIjo5NDMsImNyb3BZIjowfX0="
    },
    {
      "sourceId": "nam",
      "sourceName": "Notícias ao Minuto",
      "color": "#e07a5f",
      "title": "Cerimónia de encerramento com chuva de estrelas em intervalo extralongo",
      "link": "https://www.noticiasaominuto.com/desporto/3021486/cerimonia-de-encerramento-com-chuva-de-estrelas-em-intervalo-extralongo#utm_source=rss-ultima-hora&utm_medium=rss&utm_campaign=rssfeed",
      "pubDate": "2026-07-14 20:48:21",
      "description": "",
      "thumbnail": "https://media-manager.noticiasaominuto.com/640/naom_6a5692363d186.webp?crop_params=eyJsYW5kc2NhcGUiOnsiY3JvcFdpZHRoIjoyNTYwLCJjcm9wSGVpZ2h0IjoxNDQwLCJjcm9wWCI6MCwiY3JvcFkiOi0xfSwicG9ydHJhaXQiOnsiY3JvcFdpZHRoIjo5NDUsImNyb3BIZWlnaHQiOjE2ODAsImNyb3BYIjo3NzIsImNyb3BZIjotMX19"
    },
    {
      "sourceId": "pplware",
      "sourceName": "Pplware",
      "color": "#5bc4d4",
      "title": "Novo chip M7 Ultra da Apple triplicará a memória dos computadores Mac mais potentes",
      "link": "https://pplware.sapo.pt/apple/novo-chip-m7-ultra-da-apple-triplicara-a-memoria-dos-computadores-mac-mais-potentes/",
      "pubDate": "Tue, 14 Jul 2026 19:30:52 +0000",
      "description": "A Apple está a planear uma autêntica revolução na sua linha Mac ao preparar o lançamento do processador M7 Ultra. Este novo componente disponibilizará uma capacidade de memória unificada nunca antes vista no mercado.&#46;&#46;&#46;",
      "thumbnail": "https://pplware.sapo.pt/wp-content/uploads/2026/07/apple-m7.webp"
    },
    {
      "sourceId": "pplware",
      "sourceName": "Pplware",
      "color": "#5bc4d4",
      "title": "Windows 11: Copilot ajudará um PC lento e uma das respostas é esta IA",
      "link": "https://pplware.sapo.pt/microsoft/windows/windows-11-copilot-ajudara-um-pc-lento-e-uma-das-respostas-e-esta-ia/",
      "pubDate": "Tue, 14 Jul 2026 18:30:36 +0000",
      "description": "A Microsoft está a testar o PC Insights no Copilot para Windows 11. Esta funcionalidade analisa o desempenho do PC e ajuda o utilizador a gerir o sistema. No entanto, traz uma contradição. O&#46;&#46;&#46;",
      "thumbnail": "https://pplware.sapo.pt/wp-content/uploads/2024/02/copilot_microsoft.jpg"
    },
    {
      "sourceId": "pplware",
      "sourceName": "Pplware",
      "color": "#5bc4d4",
      "title": "O habitat dos diferentes tipos de videojogos",
      "link": "https://pplware.sapo.pt/jogos/o-habitat-dos-diferentes-tipos-de-videojogos/",
      "pubDate": "Tue, 14 Jul 2026 18:00:14 +0000",
      "description": "Todos os géneros de videojogos têm o seu habitat natural. Apesar de poderem ser jogados em praticamente qualquer lado, existem certos locais onde claramente certos tipos de jogos podem&#8230; ou melhor&#8230; devem ser desfrutados&#46;&#46;&#46;",
      "thumbnail": "https://pplware.sapo.pt/wp-content/uploads/2026/07/HabitatGaming_3.jpg"
    },
    {
      "sourceId": "pplware",
      "sourceName": "Pplware",
      "color": "#5bc4d4",
      "title": "EUA têm uma versão moderna da PIDE? Quem faz críticas online recebe uma visita em casa",
      "link": "https://pplware.sapo.pt/internet/eua-tem-uma-versao-moderna-da-pide-quem-faz-criticas-online-recebe-uma-visita-em-casa/",
      "pubDate": "Tue, 14 Jul 2026 17:00:22 +0000",
      "description": "Nos Estados Unidos da América (EUA), criticar publicamente o Serviço de Imigração e Fiscalização Aduaneira (em inglês, ICE) já resulta numa visita inesperada de agentes federais a casa. Sem mandado judicial, sem acusação e,&#46;&#46;&#46;",
      "thumbnail": "https://pplware.sapo.pt/wp-content/uploads/2026/07/vigilancia-redes-sociais02.jpg"
    },
    {
      "sourceId": "pplware",
      "sourceName": "Pplware",
      "color": "#5bc4d4",
      "title": "Portugal: Fortinet alerta para “espião digital” de contas bancárias",
      "link": "https://pplware.sapo.pt/internet/portugal-fortinet-alerta-para-espiao-digital-de-contas-bancarias/",
      "pubDate": "Tue, 14 Jul 2026 16:00:16 +0000",
      "description": "Os investigadores da Fortinet alertam para uma nova campanha de cibercrime que está a atingir utilizadores de banca online em Portugal e Espanha. Em causa está o Ousaban, um trojan bancário que evoluiu significativamente&#46;&#46;&#46;",
      "thumbnail": "https://pplware.sapo.pt/wp-content/uploads/2020/10/cgd.jpg"
    },
    {
      "sourceId": "autosport",
      "sourceName": "Autosport",
      "color": "#f0c040",
      "title": "F1: McLaren trabalha para alargar janela operacional do MCL40",
      "link": "https://www.autosport.pt/formula1/f1-mclaren-trabalha-para-alargar-janela-operacional-do-mcl40/",
      "pubDate": "Tue, 14 Jul 2026 16:15:37 +0000",
      "description": "A McLaren tem procurado entender os motivos da flutuação de performance ao longo da temporada e há algumas fragilidades que começam a ser percebidas. Essas fragilidades foi explicada por Oscar Piastri, que referiu sensibilidade excessiva do MCL40 a condições de vento mais severo como uma das causas ",
      "thumbnail": ""
    },
    {
      "sourceId": "autosport",
      "sourceName": "Autosport",
      "color": "#f0c040",
      "title": "Vila Real, CPV: Batina Racing soma pontos importantes",
      "link": "https://www.autosport.pt/velocidade/vila-real-cpv-batina-racing-soma-pontos-importantes/",
      "pubDate": "Tue, 14 Jul 2026 15:09:45 +0000",
      "description": "A Batina Racing regressou de Vila Real com dois pódios na divisão GT4 Pro-Bronze, na terceira etapa do Supercars Endurance, pontuável para o Campeonato de Portugal de Velocidade e integrada na 55.ª edição do Circuito Internacional de Vila Real. Apesar de um fim de semana marcado por alguns contratem",
      "thumbnail": ""
    },
    {
      "sourceId": "autosport",
      "sourceName": "Autosport",
      "color": "#f0c040",
      "title": "Ni Amorim: “Itália é, neste momento, uma opção mais forte para receber quer o WEC, quer a F1”",
      "link": "https://www.autosport.pt/formula1/ni-amorim-italia-e-neste-momento-uma-opcao-mais-forte-para-receber-quer-o-wec-quer-a-f1/",
      "pubDate": "Tue, 14 Jul 2026 14:35:16 +0000",
      "description": "Ni Amorim, presidente da FPAK, abordou os rumores sobre a possível vinda do WEC e da Fórmula 1 a Portimão, mostrando-se cauteloso e sublinhando que os rumores que agora circulam podem não corresponder à realidade. Em declarações ao AutoSport em Vila Real, Ni Amorim foi pragmático face aos mais recen",
      "thumbnail": ""
    },
    {
      "sourceId": "autosport",
      "sourceName": "Autosport",
      "color": "#f0c040",
      "title": "F1: James Vowles admite desilusão com as atualizações",
      "link": "https://www.autosport.pt/formula1/f1-james-vowles-admite-desilusao-com-as-atualizacoes/",
      "pubDate": "Tue, 14 Jul 2026 14:02:17 +0000",
      "description": "James Vowles, diretor da Williams, reconheceu que as atualizações introduzidas pela equipa no Grande Prémio de Grã-Bretanha ficaram muito abaixo do necessário para inverter a atual quebra de resultados. O arranque desta nova era, que se esperava auspicioso para a equipa de Grove, tem sido o oposto. ",
      "thumbnail": ""
    },
    {
      "sourceId": "autosport",
      "sourceName": "Autosport",
      "color": "#f0c040",
      "title": "CPM, Rampa Capital do Móvel: 77 pilotos inscritos",
      "link": "https://www.autosport.pt/destaque-homepage/cpm-rampa-capital-do-movel-77-pilotos-inscritos/",
      "pubDate": "Tue, 14 Jul 2026 12:03:49 +0000",
      "description": "A 7.ª Rampa Capital do Móvel, quinta prova do Campeonato de Portugal de Montanha JC Group de 2026, realiza-se no próximo fim de semana em Paços de Ferreira, com a presença de 77 pilotos. A ausência do pentacampeão Hélder Silva coloca José Correia no papel de favorito, mas Tomás Pinto, Gonçalo Inácio",
      "thumbnail": ""
    }
  ]
}