{
  "updated": "2026-07-16T11:59:38.281109+00:00",
  "articles": [
    {
      "sourceId": "observador",
      "sourceName": "Observador",
      "color": "#e8a84c",
      "title": "Ministro diz que faltam professores para classificar exames",
      "link": "https://observador.pt/2026/07/16/ministro-diz-que-faltam-professores-para-classificar-exames-em-falta-estao-por-classificar-07-dos-itens/",
      "pubDate": "Thu, 16 Jul 2026 12:55:45 +0100",
      "description": "\"Estamos com dificuldades em conseguir que haja professores classificadores para algumas provas\", assumiu Fernando Alexandre.",
      "thumbnail": "https://bordalo.observador.pt/v2/rs:fill:770:403/c:2000:1124:nowe:0:105/q:70/plain/https://s3.observador.pt/wp-content/uploads/2026/07/15102116/47464866.jpg"
    },
    {
      "sourceId": "observador",
      "sourceName": "Observador",
      "color": "#e8a84c",
      "title": "Debate do Estado da Nação é só um \"disco riscado\"? — Debate",
      "link": "https://observador.pt/programas/contra-corrente/debate-do-estado-da-nacao-e-so-um-disco-riscado-debate/",
      "pubDate": "Thu, 16 Jul 2026 12:22:35 +0100",
      "description": "Entre tudo bem e tudo mal, o parlamento vai hoje dividir-se para discutir o estado da nação com crises nos exames e polémicas de obras em casa de ministros à mistura.",
      "thumbnail": "https://bordalo.observador.pt/v2/rs:fill:770:403/c:770:433:nowe:0:0/q:70/plain/https://s3.observador.pt/wp-content/uploads/2025/12/16133246/770-podcast-contra-corrente-zmf-hm-hg.jpg"
    },
    {
      "sourceId": "observador",
      "sourceName": "Observador",
      "color": "#e8a84c",
      "title": "Fenprof. Professores passaram noite a corrigir exames",
      "link": "https://observador.pt/2026/07/16/professores-passaram-noite-a-corrigir-itens-dos-exames-nacionais-diz-fenprof-ministerio-criou-situacao-de-caos/",
      "pubDate": "Thu, 16 Jul 2026 12:19:48 +0100",
      "description": "Há menos de 24 horas, houve professores a receber centenas de itens para corrigir. \"Tudo isto está a criar dificuldades\" para preparar novo ano, lamenta secretário-geral da Fenprof.",
      "thumbnail": "https://bordalo.observador.pt/v2/rs:fill:770:403/c:2000:1122:nowe:0:162/q:70/plain/https://s3.observador.pt/wp-content/uploads/2026/07/16083754/47415275.jpg"
    },
    {
      "sourceId": "observador",
      "sourceName": "Observador",
      "color": "#e8a84c",
      "title": "As notícias das 12h",
      "link": "https://observador.pt/programas/noticiario/as-noticias-das-12h-2388/",
      "pubDate": "Thu, 16 Jul 2026 12:15:59 +0100",
      "description": "As notícias na Rádio Observador. Aconteça o que acontecer.",
      "thumbnail": "https://bordalo.observador.pt/v2/rs:fill:770:403/c:770:433:nowe:0:0/q:70/plain/https://s3.observador.pt/wp-content/uploads/2026/06/15153459/770-podcast-noticiario.png"
    },
    {
      "sourceId": "observador",
      "sourceName": "Observador",
      "color": "#e8a84c",
      "title": "Estes são os 44 melhores vinhos da região de Lisboa",
      "link": "https://observador.pt/2026/07/16/estes-sao-os-44-melhores-vinhos-da-regiao-de-lisboa/",
      "pubDate": "Thu, 16 Jul 2026 11:56:26 +0100",
      "description": "O Concurso Vinhos de Lisboa distinguiu, na sua XVI edição, 9 vinhos com Grande Medalha de Ouro, 25 com Medalhas de Ouro e 10 com Medalha de Prata.",
      "thumbnail": "https://bordalo.observador.pt/v2/rs:fill:770:403/c:2048:1153:nowe:0:159/q:70/plain/https://s3.observador.pt/wp-content/uploads/2026/07/16100256/os-melhores.jpg"
    },
    {
      "sourceId": "rtp",
      "sourceName": "RTP Notícias",
      "color": "#e05252",
      "title": "12h Pautas dos exames podesm ser adiadas",
      "link": "https://www.rtp.pt/noticias/noticiario-antena1/12h-pautas-dos-exames-podesm-ser-adiadas_a1_1753762",
      "pubDate": "Thu, 16 Jul 2026 13:45:03 +0100",
      "description": "",
      "thumbnail": "https://cdn-images.rtp.pt/noticias/images/antena1_default.png?w=350&amp;q=50&amp;auto=format"
    },
    {
      "sourceId": "rtp",
      "sourceName": "RTP Notícias",
      "color": "#e05252",
      "title": "Lovro Zvonarek do Bayern de Munique para o Estrela da Amadora",
      "link": "https://www.rtp.pt/noticias/futebol-nacional/lovro-zvonarek-do-bayern-de-munique-para-o-estrela-da-amadora_d1753759",
      "pubDate": "Thu, 16 Jul 2026 13:21:48 +0100",
      "description": "O médio internacional sub-21 croata Lovro Zvonarek assinou pelo Estrela da Amadora por três épocas, após quatro anos de contrato com os alemães do Bayern de Munique, anunciou o clube português.",
      "thumbnail": "https://cdn-images.rtp.pt/icm/noticias/images/8a/8af800bef25a43f8149e1c2047cf90f6?w=350&amp;q=50&amp;rect=0,0,1499,822&amp;auto=format"
    },
    {
      "sourceId": "rtp",
      "sourceName": "RTP Notícias",
      "color": "#e05252",
      "title": "Varandas absolvido de crimes contra a honra de Pinto da Costa",
      "link": "https://www.rtp.pt/noticias/sporting/varandas-absolvido-de-crimes-contra-a-honra-de-pinto-da-costa_d1753758",
      "pubDate": "Thu, 16 Jul 2026 13:15:42 +0100",
      "description": "O Tribunal Judicial da Comarca de Viseu absolveu o presidente do Sporting de todos os crimes contra a honra e reputação de Pinto da Costa, antigo líder do FC Porto, disse hoje à Lusa fonte ligada ao processo.",
      "thumbnail": "https://cdn-images.rtp.pt/icm/noticias/images/38/385c6f651247e143d0fd53d36b4627be?w=350&amp;q=50&amp;rect=0,0,1499,822&amp;auto=format"
    },
    {
      "sourceId": "rtp",
      "sourceName": "RTP Notícias",
      "color": "#e05252",
      "title": "Políticas do Governo marcadas por \"défice de informação\", \"obsessão com a imigração\" e \"pouca redução da pobreza\"",
      "link": "https://www.rtp.pt/noticias/pais/politicas-do-governo-marcadas-por-defice-de-informacao-obsessao-com-a-imigracao-e-pouca-reducao-da-pobreza_n1753757",
      "pubDate": "Thu, 16 Jul 2026 13:03:05 +0100",
      "description": "O relatório, realizado como base em 16 ensaios realizados por investigadores do ISCTE, conclui que faltam bases sólidas às políticas que os governos da AD lançaram entre 2024 e 2026. &quot;Os resultados estão aquém dos definidos pelo próprio Governo&quot;, lê-se no documento.",
      "thumbnail": "https://cdn-images.rtp.pt/icm/noticias/images/a0/a094cba54979386ea060169d4f491e0b?w=350&amp;q=50&amp;rect=0,11,1500,822&amp;auto=format"
    },
    {
      "sourceId": "rtp",
      "sourceName": "RTP Notícias",
      "color": "#e05252",
      "title": "Ministro da Educação: faltam professores para corrigir",
      "link": "https://www.rtp.pt/noticias/noticiario-antena1/ministro-da-educacao-faltam-professores-para-corrigir_a1_1753752",
      "pubDate": "Thu, 16 Jul 2026 12:26:03 +0100",
      "description": "",
      "thumbnail": "https://cdn-images.rtp.pt/noticias/images/antena1_default.png?w=350&amp;q=50&amp;auto=format"
    },
    {
      "sourceId": "maisfutebol",
      "sourceName": "Maisfutebol",
      "color": "#4fc48a",
      "title": "OFICIAL: Famalicão renova com Matheus Mattara até 2031",
      "link": "https://maisfutebol.iol.pt/famalicao/liga/oficial-famalicao-renova-com-matheus-mattara-ate-2031",
      "pubDate": "Thu, 16 Jul 2026 12:56:24 +0100",
      "description": "Jovem central de 19 anos tem vindo a ultrapassar barreiras após barreiras",
      "thumbnail": "https://img.iol.pt/image/id/6a58c443d34ef04b4f3f6f14/250"
    },
    {
      "sourceId": "maisfutebol",
      "sourceName": "Maisfutebol",
      "color": "#4fc48a",
      "title": "Marítimo regressa à Liga e procura pelo lugar anual sobe 250 por cento",
      "link": "https://maisfutebol.iol.pt/maritimo/liga/maritimo-regressa-a-liga-e-procura-pelo-lugar-anual-sobe-250-por-cento",
      "pubDate": "Thu, 16 Jul 2026 12:27:00 +0100",
      "description": "Caldeirão dos Barreiros promete encher em 2026/27",
      "thumbnail": "https://img.iol.pt/image/id/69442eb1d34e2bd5c6d547f6/250"
    },
    {
      "sourceId": "maisfutebol",
      "sourceName": "Maisfutebol",
      "color": "#4fc48a",
      "title": "Varandas volta a ser absolvido de crimes contra a honra de Pinto da Costa",
      "link": "https://maisfutebol.iol.pt/sporting/liga/varandas-volta-a-ser-absolvido-de-crimes-contra-a-honra-de-pinto-da-costa",
      "pubDate": "Thu, 16 Jul 2026 12:11:27 +0100",
      "description": "Presidente do Sporting «protegido» pelo exercício da liberdade de expressão",
      "thumbnail": "https://img.iol.pt/image/id/69b5ff17d34e28842c81c3f4/250"
    },
    {
      "sourceId": "maisfutebol",
      "sourceName": "Maisfutebol",
      "color": "#4fc48a",
      "title": "Mundial 2026: Messi quebra recordes pessoais e espreita o «rooftop» do Olimpo",
      "link": "https://maisfutebol.iol.pt/mundial-2026/mundial2026/mundial-2026-messi-quebra-recordes-pessoais-e-espreita-o-rooftop-do-olimpo",
      "pubDate": "Thu, 16 Jul 2026 12:09:00 +0100",
      "description": "Astro alcançou o jogo com mais dribles em Mundiais, fez algo inédito em 56 anos, vive a melhor campanha e aponta a mais recordes. Se domingo for favorável à Argentina, então Messi pode reservar espaço para a nona Bola de Ouro",
      "thumbnail": "https://img.iol.pt/image/id/6a58b34bd34e511da0b2db31/250"
    },
    {
      "sourceId": "maisfutebol",
      "sourceName": "Maisfutebol",
      "color": "#4fc48a",
      "title": "Vitória espera arrecadar três milhões com quotas e lugares anuais",
      "link": "https://maisfutebol.iol.pt/vitoria-guimaraes/liga/vitoria-espera-arrecadar-tres-milhoes-com-quotas-e-lugares-anuais",
      "pubDate": "Thu, 16 Jul 2026 11:53:58 +0100",
      "description": "Clube divulgou orçamento que vai ser discutido e votado na assembleia que está marcada para 24 de julho",
      "thumbnail": "https://img.iol.pt/image/id/67788089d34ea1acf2727d25/250"
    },
    {
      "sourceId": "sapo",
      "sourceName": "SAPO",
      "color": "#9b7ee8",
      "title": "Das obras na PJ ao “amigo” empreiteiro: tudo o que sabe da polémica que envolve Luís Neves",
      "link": "https://eco.sapo.pt/2026/07/16/das-obras-na-pj-ao-amigo-empreiteiro-tudo-o-que-sabe-da-polemica-que-envolve-luis-neves/",
      "pubDate": "Thu, 16 Jul 2026 08:50:25 +0000",
      "description": "A adjudicação de obras da PJ a uma empresa que viria a remodelar a casa do ministro Luís Neves está a levantar dúvidas sobre eventuais conflitos de interesses e regularidade dos contratos públicos.",
      "thumbnail": "https://thumbs.web.sapo.io/?H=720&W=1280&crop=center&delay_optim=1&epic=V2%3AwlwQzEEht8vS0UHvWNIZmIlGMmqG1JINCFlYqeifbb7eakTxaZFcn4qDXQJXxOe4B04Dp4ZXGOrtyc8QiNINnK%2BhF5HQEED9U5Ud8%2BRn3cA15Ep7x%2FfzbYGIp75y8dwQ"
    },
    {
      "sourceId": "sapo",
      "sourceName": "SAPO",
      "color": "#9b7ee8",
      "title": "Exames nacionais: Ministro diz que “há risco de as notas não serem publicadas amanhã”",
      "link": "https://sapo.pt/artigo/exames-nacionais-ministro-diz-que-ha-risco-de-as-notas-nao-serem-publicadas-amanha-6a58a83e6b5c2e83daafec29",
      "pubDate": "Thu, 16 Jul 2026 10:07:50 +0000",
      "description": "“Há sempre riscos” de os resultados dos exames nacionais não serem afixados na próxima sexta-feira, admite Fernando Alexandre, apelando a um \"esforço adicional\" dos professores no último dia do calendário",
      "thumbnail": "https://thumbs.web.sapo.io/?H=630&W=1120&crop=center&delay_optim=1&epic=V2%3AgKL%2F5DSmDkcTf%2Bz1pSoPsJYsMRM3IGXuj1LYq73Wk2e9AdLk%2BpqlN5e8k65b1TyajPIabw6R%2FxmK8z1X6wXXiu6Dw6bx37BXOleAJaEJLScDKDoV9gT02%2F4mpTMSHk7E"
    },
    {
      "sourceId": "sapo",
      "sourceName": "SAPO",
      "color": "#9b7ee8",
      "title": "Oposição interna do PAN pede demissão de Inês Sousa Real e exige novo Congresso",
      "link": "https://sapo.pt/artigo/oposicao-interna-do-pan-pede-demissao-de-ines-sousa-real-e-exige-novo-congresso-6a58aacae2acf9d52be41757",
      "pubDate": "Thu, 16 Jul 2026 10:35:31 +0000",
      "description": "O Tribunal Constitucional declarou ilegal parte do regulamento do último Congresso do PAN e, como consequência, invalidou a última eleição da direção do partido, na qual Inês de Sousa Real foi reeleita como porta-voz. Cerca de 30 militantes...",
      "thumbnail": "https://thumbs.web.sapo.io/?H=630&W=1120&crop=center&delay_optim=1&epic=V2%3AOFMtdXxHat9ITBxuZOJAeNceeJS4gjSw80fZ04MgiUQDypkIkTAOiwFYv5nPLTv4x%2FPGlQT03w4XM7E%2BH9vwEzsgDyFti5k19YlBhLKQ06Hr5EHuk2YY%2BXWwk62U6X3e"
    },
    {
      "sourceId": "sapo",
      "sourceName": "SAPO",
      "color": "#9b7ee8",
      "title": "Do \"ministro sem professores\" à \"dama curandeira do caos”: PS lança tarot, jogos e um quiz para criticar governo",
      "link": "https://sapo.pt/artigo/do-ministro-sem-professores-a-dama-curandeira-do-caos-ps-lanca-tarot-jogos-e-um-quiz-para-criticar-governo-6a588e1c0fd7fb3f2f6f19ce",
      "pubDate": "Thu, 16 Jul 2026 08:50:25 +0000",
      "description": "Socialistas criaramm jogos online com membros do Governo para mostrar 'má governação' da AD",
      "thumbnail": "https://thumbs.web.sapo.io/?H=630&W=1120&crop=center&delay_optim=1&epic=V2%3AAuyYgWUv2AZCU2hNi%2FquPkjL2ZjpeYPUBAgxiBFYfLGmFIAG04ToluiXfbtypVkGYjQy5DGGY1kp2FwVHJS6VHGMzMWiwl5dcI8VM%2BnQrvvg%2FuvpvBozhDsyirxHwHMJ"
    },
    {
      "sourceId": "sapo",
      "sourceName": "SAPO",
      "color": "#9b7ee8",
      "title": "Governo tem “obsessão com imigração” e falha no combate à pobreza, alerta relatório do ISCTE",
      "link": "https://jornaleconomico.sapo.pt/noticias/governo-tem-obsessao-com-imigracao-e-falha-no-combate-a-pobreza-alerta-relatorio-do-iscte/",
      "pubDate": "Thu, 16 Jul 2026 08:50:25 +0000",
      "description": "Estas conclusões constam de um relatório do Instituto para as Políticas Públicas e Sociais (IPPS) do ISCTE, coordenado por Pedro Adão e Silva, ex-ministro do PS, intitulado “O Estado da nação e as políticas públicas 2026”.",
      "thumbnail": "https://thumbs.web.sapo.io/?H=660&W=1174&crop=center&delay_optim=1&epic=V2%3AbOwfFCqMCd4fHKphkXEJd0qcKl0HwYKFjiNaanfWywxXz94J32p5FAm%2BQieXEZFLNdQRbR200t%2BU8TPhz4LOBp%2FGBnYPft3oVGcKJt6gmfL2d1T1ARYn4Tf3V6sLEr%2Bi"
    },
    {
      "sourceId": "nam",
      "sourceName": "Notícias ao Minuto",
      "color": "#e07a5f",
      "title": "Serpa. Suspeito de maus-tratos a bebé que morreu desconhecia investigação",
      "link": "https://www.noticiasaominuto.com/pais/3022477/serpa-suspeito-de-maus-tratos-a-bebe-que-morreu-desconhecia-investigacao#utm_source=rss-ultima-hora&utm_medium=rss&utm_campaign=rssfeed",
      "pubDate": "2026-07-16 12:57:29",
      "description": "",
      "thumbnail": "https://media-manager.noticiasaominuto.com/640/naom_688e92fcc8c85.webp"
    },
    {
      "sourceId": "nam",
      "sourceName": "Notícias ao Minuto",
      "color": "#e07a5f",
      "title": "\"Responsabilidade não é dos professores\" pelo \"caos que o Governo lançou\"",
      "link": "https://www.noticiasaominuto.com/politica/3022469/responsabilidade-nao-e-dos-professores-pelo-caos-que-o-governo-lancou#utm_source=rss-ultima-hora&utm_medium=rss&utm_campaign=rssfeed",
      "pubDate": "2026-07-16 12:48:10",
      "description": "",
      "thumbnail": "https://media-manager.noticiasaominuto.com/640/naom_67fe9936b5fde.webp"
    },
    {
      "sourceId": "nam",
      "sourceName": "Notícias ao Minuto",
      "color": "#e07a5f",
      "title": "Oficial: Vivaldo Semedo está de volta a Portugal para jogar no Alverca",
      "link": "https://www.noticiasaominuto.com/desporto/3022466/oficial-vivaldo-semedo-esta-de-volta-a-portugal-para-jogar-no-alverca#utm_source=rss-ultima-hora&utm_medium=rss&utm_campaign=rssfeed",
      "pubDate": "2026-07-16 12:47:18",
      "description": "",
      "thumbnail": "https://media-manager.noticiasaominuto.com/640/naom_6a58c49e5c315.webp?crop_params=eyJsYW5kc2NhcGUiOnsiY3JvcFdpZHRoIjoxMDgwLCJjcm9wSGVpZ2h0Ijo2MDgsImNyb3BYIjowLCJjcm9wWSI6MTg0fX0="
    },
    {
      "sourceId": "nam",
      "sourceName": "Notícias ao Minuto",
      "color": "#e07a5f",
      "title": "\"Cristiano Ronaldo ainda tem nível para a Arábia, mas para um Mundial...\"",
      "link": "https://www.noticiasaominuto.com/desporto/3022472/cristiano-ronaldo-ainda-tem-nivel-para-a-arabia-mas-para-um-mundial#utm_source=rss-ultima-hora&utm_medium=rss&utm_campaign=rssfeed",
      "pubDate": "2026-07-16 12:45:11",
      "description": "",
      "thumbnail": "https://media-manager.noticiasaominuto.com/640/naom_6a4c1d9c0b29c.webp?crop_params=eyJsYW5kc2NhcGUiOnsiY3JvcFdpZHRoIjoyNTYwLCJjcm9wSGVpZ2h0IjoxNDQwLCJjcm9wWCI6MCwiY3JvcFkiOjIxfX0="
    },
    {
      "sourceId": "nam",
      "sourceName": "Notícias ao Minuto",
      "color": "#e07a5f",
      "title": "Ministro da Defesa cessante acusa chefe militar de querer dividir Ucrânia",
      "link": "https://www.noticiasaominuto.com/mundo/3022471/ministro-da-defesa-cessante-acusa-chefe-militar-de-querer-dividir-ucrania#utm_source=rss-ultima-hora&utm_medium=rss&utm_campaign=rssfeed",
      "pubDate": "2026-07-16 12:43:57",
      "description": "",
      "thumbnail": "https://media-manager.noticiasaominuto.com/640/naom_6a58c4049906a.webp"
    },
    {
      "sourceId": "pplware",
      "sourceName": "Pplware",
      "color": "#5bc4d4",
      "title": "20-20-20: a regra que promete salvar os seus olhos dos ecrãs",
      "link": "https://pplware.sapo.pt/gadgets/20-20-20-a-regra-que-promete-salvar-os-seus-olhos-dos-ecras/",
      "pubDate": "Thu, 16 Jul 2026 11:00:50 +0000",
      "description": "Passa o dia a olhar para o smartphone, o computador ou a televisão? Os olhos podem estar a pagar a fatura. Conheça a regra 20-20-20, uma técnica popular entre oftalmologistas para combater a fadiga&#46;&#46;&#46;",
      "thumbnail": "https://pplware.sapo.pt/wp-content/uploads/2026/07/fadiga-ocular-tempo-de-ecra01-1.jpg"
    },
    {
      "sourceId": "pplware",
      "sourceName": "Pplware",
      "color": "#5bc4d4",
      "title": "Fim desta gigante? OnePlus vai abandonar os mercados da Europa e dos EUA",
      "link": "https://pplware.sapo.pt/smartphones-tablets/android/fim-desta-gigante-oneplus-vai-abandonar-os-mercados-da-europa-e-dos-eua/",
      "pubDate": "Thu, 16 Jul 2026 10:30:53 +0000",
      "description": "A conhecida fabricante de smartphones OnePlus está a preparar-se para uma mudança radical na sua estrutura e na sua política. A marca que já teve tanto sucesso vai agora sair dos mercados da Europa&#46;&#46;&#46;",
      "thumbnail": "https://pplware.sapo.pt/wp-content/uploads/2026/07/07t7TikQxvXDMYyHrKmOycE-1.fit_lim.size_1600x900.v1784016481.webp"
    },
    {
      "sourceId": "pplware",
      "sourceName": "Pplware",
      "color": "#5bc4d4",
      "title": "Nesta capital, é proibido ter um carro que não seja branco (ou esteja sujo)",
      "link": "https://pplware.sapo.pt/motores/nesta-capital-e-proibido-ter-um-carro-que-nao-seja-branco-ou-esteja-sujo/",
      "pubDate": "Thu, 16 Jul 2026 10:00:19 +0000",
      "description": "Desde 2015 que a capital do Turquemenistão proíbe a circulação de carros coloridos. Hoje, as ruas de Ashgabat são um mar de veículos brancos, e a explicação oficial nunca chegou a existir. Uma cidade&#46;&#46;&#46;",
      "thumbnail": "https://pplware.sapo.pt/wp-content/uploads/2026/07/carro-branco-ashgabat-turquemenistao01.jpg"
    },
    {
      "sourceId": "pplware",
      "sourceName": "Pplware",
      "color": "#5bc4d4",
      "title": "Xiaomi lança o HyperOS 3.3 com o Android 17! Estes smartphones recebem já",
      "link": "https://pplware.sapo.pt/smartphones-tablets/android/xiaomi-lanca-o-hyperos-3-3-com-o-android-17-estes-smartphones-recebem-ja/",
      "pubDate": "Thu, 16 Jul 2026 09:30:30 +0000",
      "description": "Há algum tempo que circulam rumores sobre o trabalho da Xiaomi com o HyperOS e uma quarta versão. Esta representaria uma das mais profundas renovações do firmware da Xiaomi. A fabricante ainda não está&#46;&#46;&#46;",
      "thumbnail": "https://pplware.sapo.pt/wp-content/uploads/2026/07/xiaomi_17T_pro_01.jpg"
    },
    {
      "sourceId": "pplware",
      "sourceName": "Pplware",
      "color": "#5bc4d4",
      "title": "Waze: sabe o que significam as cores das estradas? Há um significado para cada uma",
      "link": "https://pplware.sapo.pt/motores/waze-sabe-o-que-significam-as-cores-das-estradas-ha-um-significado-para-cada-uma/",
      "pubDate": "Thu, 16 Jul 2026 09:00:05 +0000",
      "description": "O Waze é uma das aplicações de navegação mais populares do mundo, muito graças aos alertas em tempo real fornecidos pela comunidade. No entanto, há um detalhe que muitos utilizadores ignoram: as diferentes cores&#46;&#46;&#46;",
      "thumbnail": "https://pplware.sapo.pt/wp-content/uploads/2026/07/waze_cores00.webp"
    },
    {
      "sourceId": "autosport",
      "sourceName": "Autosport",
      "color": "#f0c040",
      "title": "Eifel Rallye Festival: ‘Thunderstruck’ do asfalto em Daun",
      "link": "https://www.autosport.pt/ralis/eifel-rallye-festival-thunderstruck-do-asfalto-em-daun/",
      "pubDate": "Thu, 16 Jul 2026 10:26:33 +0000",
      "description": "A Vulkaneifel prepara-se para acolher, entre 23 e 25 de julho de 2026, a 14ª edição do ADAC Eifel Rallye Festival, um encontro internacional que reúne mais de 160 veículos históricos originais ou reconstruídos com rigor. O evento, que transforma a região em torno de Daun num museu itinerante da hist",
      "thumbnail": ""
    },
    {
      "sourceId": "autosport",
      "sourceName": "Autosport",
      "color": "#f0c040",
      "title": "WRC: Oliver Solberg procura redenção sob forte pressão competitiva",
      "link": "https://www.autosport.pt/ralis/wrc-oliver-solberg-procura-redencao-sob-forte-pressao-competitiva/",
      "pubDate": "Thu, 16 Jul 2026 10:16:12 +0000",
      "description": "O Rali da Estónia, nona etapa do Campeonato Mundial de Ralis, marca o regresso de Oliver Solberg ao palco da sua primeira vitória absoluta na competição, celebrada há um ano. O piloto sueco, atualmente quinto classificado no campeonato, chega a Tartu determinado a inverter uma sequência de resultado",
      "thumbnail": ""
    },
    {
      "sourceId": "autosport",
      "sourceName": "Autosport",
      "color": "#f0c040",
      "title": "Campeonato Norte de Ralis prossegue com Rally Rota da Cereja de Resende",
      "link": "https://www.autosport.pt/ralis/campeonato-norte-de-ralis-prossegue-com-rally-rota-da-cereja-de-resende/",
      "pubDate": "Thu, 16 Jul 2026 09:34:47 +0000",
      "description": "Realiza-se no próximo fim de semana a quinta prova do Campeonato Norte de Ralis, o 3º Rally Rota da Cereja de Resende, prova de asfalto organizada pela Associação Team Baia. Rafael Cunha / Gonçalo Cunha (Ford Fiesta R200) lideram o campeonato com 68 pontos mesmo não tendo ainda vencido qualquer prov",
      "thumbnail": ""
    },
    {
      "sourceId": "autosport",
      "sourceName": "Autosport",
      "color": "#f0c040",
      "title": "WRC, Rali da Estónia: O que dizem os chefes de equipa da Toyota, Hyundai e M-Sport",
      "link": "https://www.autosport.pt/ralis/wrc-rali-da-estonia-o-que-dizem-os-chefes-de-equipa-da-toyota-hyundai-e-m-sport/",
      "pubDate": "Thu, 16 Jul 2026 08:38:21 +0000",
      "description": "O Mundial de Ralis regressa à ação com a nona prova da temporada, o Rali da Estónia, a decorrer entre 17 e 19 de julho. Após a dureza do Rali da Acrópole, na Grécia, as equipas enfrentam agora troços de terra extremamente rápidos, onde as médias de velocidade superam frequentemente os 120 km/h, exig",
      "thumbnail": ""
    },
    {
      "sourceId": "autosport",
      "sourceName": "Autosport",
      "color": "#f0c040",
      "title": "Roope Korhonen lidera a caravana do WRC2 no Rali da Estónia",
      "link": "https://www.autosport.pt/ralis/roope-korhonen-lidera-a-caravana-do-wrc2-no-rali-da-estonia/",
      "pubDate": "Thu, 16 Jul 2026 08:25:44 +0000",
      "description": "O finlandês Roope Korhonen parte para o Rali da Estónia com o objetivo de consolidar a sua liderança no WRC2. Após o quarto lugar na Grécia, que lhe permitiu ascender ao topo da classificação com três pontos de vantagem sobre Alejandro Cachón, o piloto procura capitalizar a ausência de vários rivais",
      "thumbnail": ""
    }
  ]
}